md2py/__init__.py
md2py/md2py.py
md2py-0.0.1.dist-info/LICENSE
md2py-0.0.1.dist-info/METADATA
md2py-0.0.1.dist-info/WHEEL
md2py-0.0.1.dist-info/top_level.txt
md2py-0.0.1.dist-info/RECORD
